README
setup.cfg
setup.py
bluepy/Makefile
bluepy/__init__.py
bluepy/bluepy-helper.c
bluepy/bluez-src.tgz
bluepy/btle.py
bluepy/get_services.py
bluepy/sensortag.py
bluepy/uuids.json
bluepy.egg-info/PKG-INFO
bluepy.egg-info/SOURCES.txt
bluepy.egg-info/dependency_links.txt
bluepy.egg-info/entry_points.txt
bluepy.egg-info/top_level.txt