Metadata-Version: 1.1
Name: bluepy
Version: 1.0.3
Summary: Python module for interfacing with BLE devices through Bluez
Home-page: https://github.com/IanHarvey/bluepy
Author: Ian Harvey
Author-email: website-contact@fenditton.org
License: UNKNOWN
Download-URL: https://github.com/IanHarvey/bluepy/tarball/v/1.0.3
Keywords: Bluetooth,Bluetooth Smart,BLE,Bluetooth Low Energy
Platform: UNKNOWN
Classifier: Programming Language :: Python :: 2.7
Classifier: Programming Language :: Python :: 3.3
Classifier: Programming Language :: Python :: 3.4
